{"is_source_file": true, "format": "Kotlin", "description": "Defines the MainActivity class for an Android application, extending AppCompatActivity, and sets the content view during creation.", "external_files": ["R.layout.activity_main"], "external_methods": ["setContentView"], "published": ["MainActivity"], "classes": [{"name": "MainActivity", "description": "Main activity class for the Android app, handles creation lifecycle, extends AppCompatActivity."}], "methods": [{"name": "onCreate", "description": "Lifecycle method called when the activity is starting, sets up initial UI."}], "calls": ["super.onCreate", "setContentView"], "search-terms": ["MainActivity", "Android", "AppCompatActivity", "onCreate", "activity_main"], "state": 2, "file_id": 7, "knowledge_revision": 20, "git_revision": "c352d6335049f7b22a7dd6ad92d33132064217c7", "hash": "c69070ff25468b14e7514f49a7086c2b", "format-version": 4, "code-base-name": "notes_frontend", "filename": "notes_frontend/app/src/main/java/com/example/notesfrontend/MainActivity.kt", "revision_history": [{"20": "c352d6335049f7b22a7dd6ad92d33132064217c7"}]}